setup.py
lib/silme/__init__.py
lib/silme.egg-info/PKG-INFO
lib/silme.egg-info/SOURCES.txt
lib/silme.egg-info/dependency_links.txt
lib/silme.egg-info/top_level.txt
lib/silme/core/__init__.py
lib/silme/core/entity.py
lib/silme/core/logger.py
lib/silme/core/object.py
lib/silme/diff/__init__.py
lib/silme/diff/blob.py
lib/silme/diff/entity.py
lib/silme/diff/entitylist.py
lib/silme/diff/l10nobject.py
lib/silme/diff/package.py
lib/silme/format/__init__.py
lib/silme/format/dtd/__init__.py
lib/silme/format/dtd/parser.py
lib/silme/format/dtd/serializer.py
lib/silme/format/dtd/structure.py
lib/silme/format/gettext/__init__.py
lib/silme/format/gettext/parser.py
lib/silme/format/gettext/serializer.py
lib/silme/format/gettext/structure.py
lib/silme/format/html/__init__.py
lib/silme/format/html/parser.py
lib/silme/format/html/serializer.py
lib/silme/format/html/structure.py
lib/silme/format/inc/__init__.py
lib/silme/format/inc/parser.py
lib/silme/format/inc/serializer.py
lib/silme/format/inc/structure.py
lib/silme/format/ini/__init__.py
lib/silme/format/ini/parser.py
lib/silme/format/ini/serializer.py
lib/silme/format/ini/structure.py
lib/silme/format/l20n/__init__.py
lib/silme/format/l20n/parser.py
lib/silme/format/l20n/structure.py
lib/silme/format/properties/__init__.py
lib/silme/format/properties/parser.py
lib/silme/format/properties/serializer.py
lib/silme/format/properties/structure.py
lib/silme/format/text/__init__.py
lib/silme/format/text/serializer.py
lib/silme/io/__init__.py
lib/silme/io/clients.py
lib/silme/io/file.py
lib/silme/io/hg.py
lib/silme/io/jar.py
lib/silme/io/mysql.py
lib/silme/io/sqlite.py
lib/silme/io/svn.py